intervalpylib/AreaCalculator.py
intervalpylib/Solvers.py
intervalpylib/SymbolicEquationSolver.py
intervalpylib/__init__.py
intervalpylib-0.1.2.dist-info/LICENSE
intervalpylib-0.1.2.dist-info/METADATA
intervalpylib-0.1.2.dist-info/WHEEL
intervalpylib-0.1.2.dist-info/top_level.txt
intervalpylib-0.1.2.dist-info/RECORD
