Metadata-Version: 2.1
Name: intervalpylib
Version: 0.1.2
Summary: An interval solver for robots' workspace area
Author-email: Schukark <schukark2004@gmail.com>
Project-URL: Homepage, https://github.com/schukark/intervalpylib
Project-URL: Issues, https://github.com/schukark/intervalpylib/issues
Classifier: Programming Language :: Python :: 3
Classifier: License :: OSI Approved :: Apache Software License
Classifier: Operating System :: OS Independent
Requires-Python: >=3.10
License-File: LICENSE
Requires-Dist: interval-py ==0.0.3.1
Requires-Dist: matplotlib ==3.8.4
Requires-Dist: numpy ==1.26.4
Requires-Dist: sympy ==1.12
